{
  "Prenotato il": 1,
  "Cancellata il": 2,
  "Gg di anticipo prenotazione": 3,
  "Gg di anticipo cancellazione": 4,
  "Stato prenotazione": 5,
  "Tipo tariffa": 6,
  "Dettaglio tariffa": 7,
  "Genius": 8,
  "Promozioni": 9,
  "Gg. rimborsabile": 10,
  "Entrata": 11,
  "Uscita": 12,
  "Giorni": 13,
  "Residenza": 14,
  "App. prenotato": 15,
  "App. assegnato": 16,
  "Rif. Inq": 17,
  "Nazionalità": 18,
  "Motivo soggiorno": 19,
  "Persone": 20,
  "Importo notte": 21,
  "Importo totale": 80,
  "Costo pulizie": 23,
  "Comm. Servizio": 24,
  "Comm. Riscossione": 25,
  "Tassa di soggiorno": 26,
  "Netto a noi": 27,
  "Ricevuta fiscale con IVA": 28,
  "Ricevuta fiscale esclusa IVA": 29,
  "Fatta ricevuta": 30,
  "Data ricevuta": 31,
  "Fatto saldo": 32,
  "Data saldo": 33,
  "Totale ricevuta fiscale": 34,
  "Pagato su": 35,
  "Tramite": 36,
  "Netto ricevuto": 37,
  "Commissioni bancarie": 38,
  "%": 39,
  "Incassato": 40,
  "Note": 41,
  "Fatto check-in": 42,
  "Pagato check-in": 43,
  "Fatta recensione": 44,
  "Totale": 79,
  "Giorno 1": 48,
  "Giorno 2": 49,
  "Giorno 3": 50,
  "Giorno 4": 51,
  "Giorno 5": 52,
  "Giorno 6": 53,
  "Giorno 7": 54,
  "Giorno 8": 55,
  "Giorno 9": 56,
  "Giorno 10": 57,
  "Giorno 11": 58,
  "Giorno 12": 59,
  "Giorno 13": 60,
  "Giorno 14": 61,
  "Giorno 15": 62,
  "Giorno 16": 63,
  "Giorno 17": 64,
  "Giorno 18": 65,
  "Giorno 19": 66,
  "Giorno 20": 67,
  "Giorno 21": 68,
  "Giorno 22": 69,
  "Giorno 23": 70,
  "Giorno 24": 71,
  "Giorno 25": 72,
  "Giorno 26": 73,
  "Giorno 27": 74,
  "Giorno 28": 75,
  "Giorno 29": 76,
  "Giorno 30": 77,
  "Giorno 31": 78
}